aliyunsdkthreedvision/__init__.py
aliyunsdkthreedvision/endpoint.py
aliyunsdkthreedvision/request/__init__.py
aliyunsdkthreedvision/request/v20210131/EstimateMonocularImageDepthRequest.py
aliyunsdkthreedvision/request/v20210131/EstimateMonocularVideoDepthRequest.py
aliyunsdkthreedvision/request/v20210131/EstimateStereoImageDepthRequest.py
aliyunsdkthreedvision/request/v20210131/GetAsyncJobResultRequest.py
aliyunsdkthreedvision/request/v20210131/ReconstructBodyBySingleImageRequest.py
aliyunsdkthreedvision/request/v20210131/ReconstructThreeDMultiViewRequest.py
aliyunsdkthreedvision/request/v20210131/__init__.py
aliyun_python_sdk_threedvision-1.0.4.dist-info/LICENSE
aliyun_python_sdk_threedvision-1.0.4.dist-info/METADATA
aliyun_python_sdk_threedvision-1.0.4.dist-info/WHEEL
aliyun_python_sdk_threedvision-1.0.4.dist-info/top_level.txt
aliyun_python_sdk_threedvision-1.0.4.dist-info/RECORD
